greetings_osama/__init__.py
greetings_osama/py.typed
greetings_osama-0.1.1.dist-info/METADATA
greetings_osama-0.1.1.dist-info/WHEEL
greetings_osama-0.1.1.dist-info/RECORD
