Metadata-Version: 2.4
Name: greetings-osama
Version: 0.1.1
Summary: A tiny package to greet a person by name.
Author-email: osamahasanone <osamahasanone@gmail.com>
Requires-Python: >=3.10
